{
  "id": "b4996879-e2d8-41b7-89c0-46e762d93af8",
  "name": "Login",
  "description": "Login for token",
  "deserializeAs": "RequestTask",
  "request": {
    "url": "{{okapi}}/authn/login",
    "method": "POST",
    "contentType": "application/json",
    "accept": "application/json",
    "bodyTemplate": "{\"username\": \"{{username}}\",\"password\": \"{{password}}\"}"
  },
  "inputVariables": [],
  "headerOutputVariables": [
    {
      "key": "X-Okapi-Token",
      "type": "PROCESS"
    }
  ],
  "outputVariable": {
    "key": "loginResponse",
    "type": "PROCESS"
  },
  "asyncBefore": true
}
