{
  "id": "e8111225-c66c-466a-8552-5dd50b09a206",
  "name": "Enhance Holding Reference Links MSDB",
  "delegate": "enhancingExtractorDelegate",
  "deserializeAs": "StreamingExtractorTask",
  "streaming": true,
  "enhancementComparisons": [
    {
      "sourceProperty": "/MFHD_ID",
      "targetProperty": "/externalReference"
    },
    {
      "sourceProperty": "/SCHEMA",
      "targetProperty": "/typeName"
    }
  ],
  "enhancementMappings": [
    {
      "toProperty": "folioReference",
      "fromProperty": "/folioReference"
    },
    {
      "toProperty": "reference",
      "fromProperty": "/reference"
    }
  ],
  "mergeStrategy": "ENHANCE",
  "streamSource": "{{mod-external-reference-resolver-internal}}/streaming/referenceLinks/type/e7fbdcf5-8fb0-417e-b477-6ee9d6832f12/join/f8252895-6bf5-4458-8a3f-57bd8c36c6ba"
}
